[
  {
    "id": 10001,
    "stats": [
      {
        "statType": 0,
        "value": 100
      },
      {
        "statType": 1,
        "value": 1
      },
      {
        "statType": 2,
        "value": 1
      },
      {
        "statType": 3,
        "value": 1
      },
      {
        "statType": 4,
        "value": 10
      },
      {
        "statType": 5,
        "value": 360
      },
      {
        "statType": 6,
        "value": 3
      },
      {
        "statType": 12,
        "value": 1000
      }
    ]
  },
  {
    "id": 20001,
    "stats": [
      {
        "statType": 0,
        "value": 100
      },
      {
        "statType": 3,
        "value": 20
      }
    ]
  },
  {
    "id": 50001,
    "stats": [
      {
        "statType": 7,
        "value": 100
      },
      {
        "statType": 10,
        "value": 2
      },
      {
        "statType": 11,
        "value": 0.5
      }
    ]
  },
  {
    "id": 50002,
    "stats": [
      {
        "statType": 10,
        "value": 10
      }
    ]
  }
]
